aiotiktok/__init__.py
aiotiktok/__meta__.py
aiotiktok/client.py
aiotiktok/exceptions.py
aiotiktok/types.py
aiotiktok-3.0.0.dist-info/METADATA
aiotiktok-3.0.0.dist-info/WHEEL
aiotiktok-3.0.0.dist-info/licenses/LICENSE
aiotiktok-3.0.0.dist-info/RECORD
