Metadata-Version: 2.3
Name: aiotiktok
Version: 3.0.0
Summary: Tool for parse tiktok data
Project-URL: Homepage, https://github.com/sheldygg/aiotiktok
Author: sheldy
License-Expression: MIT
License-File: LICENSE
Classifier: Programming Language :: Python :: 3.9
Classifier: Programming Language :: Python :: 3.10
Requires-Dist: aiohttp
